setup.py
bingauss/Binomialdistribution.py
bingauss/Gaussiandistribution.py
bingauss/Generaldistribution.py
bingauss/__init__.py
bingauss.egg-info/PKG-INFO
bingauss.egg-info/SOURCES.txt
bingauss.egg-info/dependency_links.txt
bingauss.egg-info/not-zip-safe
bingauss.egg-info/top_level.txt