Metadata-Version: 2.4
Name: bingauss
Version: 0.1
Summary: Gaussian and Binomial distributions, Single Inheritance
Author: Kevin Howard
Author-email: howardkc@alumni.purdue.edu
Dynamic: author
Dynamic: author-email
Dynamic: summary
